binocular/__init__.py
binocular/consts.py
binocular/db.py
binocular/disassembler.py
binocular/ghidra.py
binocular/primitives.py
binocular/rizin.py
binocular/run.py
binocular/source.py
binocular/utils.py
BINocular-1.1.dist-info/LICENSE
BINocular-1.1.dist-info/METADATA
BINocular-1.1.dist-info/WHEEL
BINocular-1.1.dist-info/entry_points.txt
BINocular-1.1.dist-info/top_level.txt
BINocular-1.1.dist-info/RECORD
